.gitignore
.readthedocs.yml
COPYING
MANIFEST.in
README.md
pyproject.toml
setup.py
docs/Makefile
docs/Picture1.png
docs/make.bat
docs/requirements.txt
docs/source/conf.py
docs/source/description.rst
docs/source/index.rst
docs/source/_templates/autosummary/attribute.rst
docs/source/_templates/autosummary/base.rst
docs/source/_templates/autosummary/class.rst
docs/source/_templates/autosummary/module.rst
src/pwspy_gui/__init__.py
src/pwspy_gui/version.py
src/pwspy_gui.egg-info/PKG-INFO
src/pwspy_gui.egg-info/SOURCES.txt
src/pwspy_gui.egg-info/dependency_links.txt
src/pwspy_gui.egg-info/entry_points.txt
src/pwspy_gui.egg-info/requires.txt
src/pwspy_gui.egg-info/top_level.txt
src/pwspy_gui/ExtraReflectanceCreator/ERWorkFlow.py
src/pwspy_gui/ExtraReflectanceCreator/__init__.py
src/pwspy_gui/ExtraReflectanceCreator/__main__.py
src/pwspy_gui/ExtraReflectanceCreator/app.py
src/pwspy_gui/ExtraReflectanceCreator/examples/4waycalib.py
src/pwspy_gui/ExtraReflectanceCreator/examples/__init__.py
src/pwspy_gui/ExtraReflectanceCreator/examples/generateExtraReflectance.py
src/pwspy_gui/ExtraReflectanceCreator/widgets/__init__.py
src/pwspy_gui/ExtraReflectanceCreator/widgets/dialog.py
src/pwspy_gui/ExtraReflectanceCreator/widgets/mainWindow.py
src/pwspy_gui/PWSAnalysisApp/App.py
src/pwspy_gui/PWSAnalysisApp/__init__.py
src/pwspy_gui/PWSAnalysisApp/__main__.py
src/pwspy_gui/PWSAnalysisApp/_roiManager.py
src/pwspy_gui/PWSAnalysisApp/applicationVars.py
src/pwspy_gui/PWSAnalysisApp/componentInterfaces.py
src/pwspy_gui/PWSAnalysisApp/dialogs.py
src/pwspy_gui/PWSAnalysisApp/mainWindow.py
src/pwspy_gui/PWSAnalysisApp/pluginInterfaces.py
src/pwspy_gui/PWSAnalysisApp/__pycache__/App.cpython-37.pyc
src/pwspy_gui/PWSAnalysisApp/__pycache__/__init__.cpython-37.pyc
src/pwspy_gui/PWSAnalysisApp/__pycache__/__main__.cpython-37.pyc
src/pwspy_gui/PWSAnalysisApp/__pycache__/applicationVars.cpython-37.pyc
src/pwspy_gui/PWSAnalysisApp/__pycache__/componentInterfaces.cpython-37.pyc
src/pwspy_gui/PWSAnalysisApp/__pycache__/dialogs.cpython-37.pyc
src/pwspy_gui/PWSAnalysisApp/__pycache__/mainWindow.cpython-37.pyc
src/pwspy_gui/PWSAnalysisApp/__pycache__/pluginInterfaces.cpython-37.pyc
