Metadata-Version: 2.1
Name: pwspy-gui
Version: 0.1.13
Summary: A collection of GUIs providing users with easy access to PWS data analysis.
Home-page: https://github.com/nanthony21/pwspy_gui
Author: Nick Anthony
Author-email: nicholas.anthony@northwestern.edu
License: UNKNOWN
Platform: UNKNOWN
Requires-Python: >=3.7,<3.10
License-File: COPYING
